setup.py
memory_usage_notifier/__init__.py
memory_usage_notifier/command_line.py
memory_usage_notifier/memory_status.py
memory_usage_notifier.egg-info/PKG-INFO
memory_usage_notifier.egg-info/SOURCES.txt
memory_usage_notifier.egg-info/dependency_links.txt
memory_usage_notifier.egg-info/entry_points.txt
memory_usage_notifier.egg-info/not-zip-safe
memory_usage_notifier.egg-info/requires.txt
memory_usage_notifier.egg-info/top_level.txt