Metadata-Version: 1.0
Name: memory-usage-notifier
Version: 1.0
Summary: RAM Status Notifier
Home-page: https://github.com/prateekM59/MemoryConsumptionNotifier
Author: Prateek Mahajan
Author-email: prateekmahajan59@gmail.com
License: MIT
Keywords: memory RAM status notifier check RAM status python checker
Platform: UNKNOWN
